glean_parser/__init__.py
glean_parser/__main__.py
glean_parser/coverage.py
glean_parser/data_review.py
glean_parser/go_server.py
glean_parser/javascript.py
glean_parser/javascript_server.py
glean_parser/kotlin.py
glean_parser/lint.py
glean_parser/markdown.py
glean_parser/metrics.py
glean_parser/parser.py
glean_parser/pings.py
glean_parser/python_server.py
glean_parser/ruby_server.py
glean_parser/rust.py
glean_parser/rust_server.py
glean_parser/swift.py
glean_parser/tags.py
glean_parser/translate.py
glean_parser/translation_options.py
glean_parser/util.py
glean_parser/validate_ping.py
glean_parser/schemas/metrics.1-0-0.schema.yaml
glean_parser/schemas/metrics.2-0-0.schema.yaml
glean_parser/schemas/pings.1-0-0.schema.yaml
glean_parser/schemas/pings.2-0-0.schema.yaml
glean_parser/schemas/tags.1-0-0.schema.yaml
glean_parser/templates/data_review.jinja2
glean_parser/templates/go_server.jinja2
glean_parser/templates/javascript.buildinfo.jinja2
glean_parser/templates/javascript.jinja2
glean_parser/templates/javascript_server.jinja2
glean_parser/templates/kotlin.buildinfo.jinja2
glean_parser/templates/kotlin.jinja2
glean_parser/templates/markdown.jinja2
glean_parser/templates/python_server.jinja2
glean_parser/templates/qmldir.jinja2
glean_parser/templates/ruby_server.jinja2
glean_parser/templates/rust.jinja2
glean_parser/templates/rust_server.jinja2
glean_parser/templates/swift.jinja2
glean_parser-18.1.1.dist-info/METADATA
glean_parser-18.1.1.dist-info/WHEEL
glean_parser-18.1.1.dist-info/entry_points.txt
glean_parser-18.1.1.dist-info/licenses/AUTHORS.md
glean_parser-18.1.1.dist-info/licenses/LICENSE
glean_parser-18.1.1.dist-info/RECORD
