Metadata-Version: 2.4
Name: glean-parser
Version: 18.1.1
Summary: Parser tools for Mozilla's Glean telemetry
Project-URL: Homepage, https://mozilla.github.io/glean
Project-URL: Repository, https://github.com/mozilla/glean_parser
Project-URL: Changelog, https://github.com/mozilla/glean_parser/blob/main/CHANGELOG.md
Author-email: The Glean Team <glean-team@mozilla.com>
License-File: AUTHORS.md
License-File: LICENSE
Classifier: Development Status :: 5 - Production/Stable
Classifier: Intended Audience :: Developers
Classifier: Natural Language :: English
Classifier: Programming Language :: Python :: 3
Classifier: Programming Language :: Python :: 3.9
Classifier: Programming Language :: Python :: 3.10
Classifier: Programming Language :: Python :: 3.11
Classifier: Programming Language :: Python :: 3.12
Classifier: Programming Language :: Python :: 3.13
Requires-Python: >=3.9
Requires-Dist: click>=7
Requires-Dist: diskcache>=4
Requires-Dist: jinja2>=2.10.1
Requires-Dist: jsonschema>=3.0.2
Requires-Dist: platformdirs>=2.4.0
Requires-Dist: pyyaml>=5.3.1
